helpers/__init__.py
helpers/logger.py
helpers/retry_handler.py
helpers/sleeper.py
pylib_helpers-0.3.126.dist-info/LICENSE
pylib_helpers-0.3.126.dist-info/WHEEL
pylib_helpers-0.3.126.dist-info/METADATA
pylib_helpers-0.3.126.dist-info/RECORD
