Metadata-Version: 2.1
Name: pylib-helpers
Version: 0.3.126
Summary: Helpers for common functional work done across several projects
Home-page: https://github.com/samarthj/pylib-helpers
License: GPL-3.0-or-later
Author: Sam
Author-email: dev@samarthj.com
Requires-Python: >=3.9,<4.0
Classifier: License :: OSI Approved :: GNU General Public License v3 or later (GPLv3+)
Classifier: Programming Language :: Python :: 3
Classifier: Programming Language :: Python :: 3.9
Classifier: Programming Language :: Python :: 3.10
Classifier: Topic :: Software Development :: Libraries :: Python Modules
Classifier: Topic :: System :: Logging
Requires-Dist: colorama (>=0.4.4,<0.5.0)
Project-URL: Bug Tracker, https://github.com/samarthj/pylib-helpers/issues
Project-URL: Repository, https://github.com/samarthj/pylib-helpers
